imaginAIry-15.0.0.data/scripts/aimg
imaginAIry-15.0.0.data/scripts/imagine
imaginairy/__init__.py
imaginairy/config.py
imaginairy/image_prompts.py
imaginairy/py.typed
imaginairy/schema.py
imaginairy/version.py
imaginairy/api/__init__.py
imaginairy/api/colorize.py
imaginairy/api/generate.py
imaginairy/api/generate_compvis.py
imaginairy/api/generate_flux.py
imaginairy/api/generate_refiners.py
imaginairy/api/upscale.py
imaginairy/api/video_sample.py
imaginairy/cli/__init__.py
imaginairy/cli/arg_schedule.py
imaginairy/cli/clickshell_mod.py
imaginairy/cli/colorize.py
imaginairy/cli/describe.py
imaginairy/cli/edit.py
imaginairy/cli/edit_demo.py
imaginairy/cli/imagine.py
imaginairy/cli/main.py
imaginairy/cli/run_api.py
imaginairy/cli/shared.py
imaginairy/cli/unslow_the_cli.py
imaginairy/cli/upscale.py
imaginairy/cli/videogen.py
imaginairy/configs/control-net-v15-pool.yaml
imaginairy/configs/control-net-v15.yaml
imaginairy/configs/stable-diffusion-v2-midas-inference.yaml
imaginairy/configs/stable-diffusion-x4-upscaling.yaml
imaginairy/configs/svd.yaml
imaginairy/configs/svd_image_decoder.yaml
imaginairy/configs/svd_xt.yaml
imaginairy/configs/svd_xt_image_decoder.yaml
imaginairy/data/DejaVuSans.ttf
imaginairy/enhancers/__init__.py
imaginairy/enhancers/blur_detect.py
imaginairy/enhancers/bool_masker.py
imaginairy/enhancers/clip_masking.py
imaginairy/enhancers/describe_image_blip.py
imaginairy/enhancers/describe_image_clip.py
imaginairy/enhancers/face_restoration_codeformer.py
imaginairy/enhancers/facecrop.py
imaginairy/enhancers/prompt_expansion.py
imaginairy/enhancers/upscale.py
imaginairy/enhancers/upscale_realesrgan.py
imaginairy/enhancers/upscale_riverwing.py
imaginairy/enhancers/phraselists/__init__.py
imaginairy/enhancers/phraselists/art-scene.txt
imaginairy/enhancers/phraselists/christmas-scene.txt
imaginairy/enhancers/phraselists/color.txt
imaginairy/enhancers/phraselists/desktop-background.txt
imaginairy/enhancers/phraselists/interior-style.txt
imaginAIry-15.0.0.dist-info/LICENSE
imaginAIry-15.0.0.dist-info/METADATA
imaginAIry-15.0.0.dist-info/WHEEL
imaginAIry-15.0.0.dist-info/top_level.txt
imaginAIry-15.0.0.dist-info/RECORD
