Metadata-Version: 2.1
Name: imaginAIry
Version: 15.0.0
Summary: AI imagined images. Pythonic generation of images.
Author: Bryce Drennan
Project-URL: Documentation, https://github.com/brycedrennan/imaginAIry/blob/master/README.md
Project-URL: Source, https://github.com/brycedrennan/imaginAIry
Requires-Python: >=3.10
License-File: LICENSE
Requires-Dist: click>=8.0.0
Requires-Dist: click-help-colors>=0.9.1
Requires-Dist: click-shell>=2.0
Requires-Dist: protobuf!=3.19.5,!=3.20.2
Requires-Dist: fastapi>=0.70.0
Requires-Dist: ftfy>=6.0.1
Requires-Dist: torch>=2.1.0
Requires-Dist: numpy>=1.22.0
Requires-Dist: tqdm>=4.64.0
Requires-Dist: diffusers>=0.30.3
Requires-Dist: Pillow>=9.1.0
Requires-Dist: psutil>5.7.3
Requires-Dist: omegaconf>=2.1.1
Requires-Dist: open-clip-torch>=2.0.0
Requires-Dist: opencv-python>=4.4.0.46
Requires-Dist: pydantic>=2.3.0
Requires-Dist: pyparsing>=3.0.0
Requires-Dist: requests>=2.28.1
Requires-Dist: jaxtyping>=0.2.23
Requires-Dist: einops>=0.3.0
Requires-Dist: safetensors>=0.4.0
Requires-Dist: scipy>=1.8
Requires-Dist: termcolor
Requires-Dist: timm!=0.9.0,!=0.9.1,>=0.4.12
Requires-Dist: torchdiffeq>=0.2.0
Requires-Dist: torchvision>=0.13.1
Requires-Dist: transformers>=4.19.2
Requires-Dist: kornia>=0.6
Requires-Dist: uvicorn>=0.16.0
Requires-Dist: spandrel>=0.1.8
Requires-Dist: optimum-quanto>=0.2.4
Requires-Dist: sentencepiece>=0.2.0
Requires-Dist: accelerate>=0.24.0
Requires-Dist: triton>=2.0.0; sys_platform != "darwin" and platform_machine != "aarch64" and sys_platform == "linux"
